symmora_math/__init__.py
symmora_math/core.py
symmora_math-0.1.0.dist-info/METADATA
symmora_math-0.1.0.dist-info/WHEEL
symmora_math-0.1.0.dist-info/top_level.txt
symmora_math-0.1.0.dist-info/RECORD
