Metadata-Version: 2.4
Name: symmora_math
Version: 0.1.0
Summary: Just for test purposes
Author-email: Alexey Simonov <symmora@mail.ru>
License: MIT
Project-URL: Homepage, https://github.com/symmora/symmora_math
Classifier: Programming Language :: Python :: 3
Classifier: License :: OSI Approved :: MIT License
Classifier: Programming Language :: Python
Requires-Python: >=3.8
